{
  "name": "mri_apply_bias",
  "tool-version": "7.4.1",
  "description": "FreeSurfer is a software package for the analysis and visualization of neuroimaging data from cross-sectional and longitudinal studies. It is developed by the Laboratory for Computational Neuroimaging at the Martinos Center for Biomedical Imaging.\n\nFreeSurfer provides full processing streams for structural and functional MRI and includes tools for linear and nonlinear registration, cortical and subcortical segmentation, cortical surface reconstruction, statistical analysis of group morphometry, diffusion MRI, PET analysis, and much more. It is also the structural MRI analysis software of choice for the Human Connectome Project.",
  "command-line": "/usr/local/freesurfer/bin/mri_apply_bias [OPTIONS] [INPUT_VOLUME] [BIAS_VOLUME] [OUTPUT_VOLUME]",
  "schema-version": "0.5",
  "inputs": [
    {
      "id": "input_volume",
      "name": "Input Volume",
      "description": "The input volume file",
      "value-key": "[INPUT_VOLUME]",
      "type": "File",
      "optional": false
    },
    {
      "id": "bias_volume",
      "name": "Bias Volume",
      "description": "The bias volume file",
      "value-key": "[BIAS_VOLUME]",
      "type": "File",
      "optional": false
    },
    {
      "id": "output_volume",
      "name": "Output Volume",
      "description": "The output volume file",
      "value-key": "[OUTPUT_VOLUME]",
      "type": "String",
      "optional": false
    }
  ],
  "output-files": [
    {
      "id": "output_volume_file",
      "name": "Output Volume File",
      "description": "Output volume after applying bias",
      "path-template": "[OUTPUT_VOLUME]",
      "optional": false
    }
  ],
  "author": "FreeSurfer Developers",
  "container-image": {
    "type": "docker",
    "image": "freesurfer/freesurfer:7.4.1"
  },
  "url": "https://github.com/freesurfer/freesurfer"
}